{
  "variantName": "cards-brand",
  "baseBlock": "cards",
  "version": "1.0.0",
  "created": "2026-02-09T17:53:00.000Z",
  "sourceContext": {
    "originUrl": "https://www.avantorsciences.com/us/en/",
    "originPage": "Avantor Sciences homepage",
    "blockPosition": "middle"
  },
  "visualCharacteristics": {
    "colorScheme": "light",
    "density": "compact",
    "purpose": "brand-showcase",
    "imagePattern": "icon"
  },
  "contentPattern": {
    "structure": "logo image + brand name",
    "buttonCount": 0,
    "imageCount": 5
  },
  "reuseGuidance": {
    "suitableFor": [
      "brand logo grids",
      "partner logos",
      "supplier showcase sections"
    ],
    "notSuitableFor": [
      "detailed product cards",
      "content-heavy cards with descriptions"
    ]
  },
  "usage": {
    "pagesUsing": ["content/us/en/index"],
    "reuseCount": 1,
    "lastUsed": "2026-02-09T17:53:00.000Z"
  }
}
